gpmpackage/__init__.py
gpmpackage/demo.py
gpmpackage-0.0.1.dist-info/DESCRIPTION.rst
gpmpackage-0.0.1.dist-info/METADATA
gpmpackage-0.0.1.dist-info/RECORD
gpmpackage-0.0.1.dist-info/WHEEL
gpmpackage-0.0.1.dist-info/metadata.json
gpmpackage-0.0.1.dist-info/top_level.txt
