Metadata-Version: 2.0
Name: gpmpackage
Version: 0.0.1
Summary: My first python package
Home-page: UNKNOWN
Author: Gerardo Perez
Author-email: gerardopemz@gmail.com
License: UNKNOWN
Keywords: python,gpm
Platform: UNKNOWN
Classifier: Development Status :: 3 - Alpha
Classifier: Intended Audience :: Education
Classifier: Programming Language :: Python :: 2
Classifier: Programming Language :: Python :: 3
Classifier: Operating System :: MacOS :: MacOS X
Classifier: Operating System :: Microsoft :: Windows
